{
  "version": 1,
  "entries": [
    {
      "content_id": "rl-2026-07-22-6b83d3c112",
      "date": "2026-07-22",
      "campaign_day": 1,
      "topic": "appointment reminders",
      "angle": "Use automation for consistency and people for exceptions",
      "headline": "Reminders should not rely on memory",
      "hook": "Reminders should not rely on memory",
      "visual_format": "workflow-cards",
      "keywords": [
        "scheduling",
        "customers",
        "follow-up",
        "business automation",
        "Sydney business"
      ],
      "source_urls": [],
      "article_slug": "reminders-should-not-rely-on-memory",
      "image_path": "/generated/drafts/2026-07-22/hero.webp",
      "caption_hash": "bcaa9aad61da0c6611dd1fca4e3f46ebdf4d23a0a56dac435ecd9c8b9273a925",
      "article_hash": "757b4ef7a9a7245f00e945ff4c1f9c8f47f7200145949f6ad744f0334808c4fb",
      "status": "generated",
      "website_url": "",
      "instagram_media_id": "",
      "promotion_score": 76,
      "created_at": "2026-07-21T22:03:31.493Z",
      "published_at": "",
      "error": null
    },
    {
      "content_id": "rl-2026-07-23-858993ad9c",
      "date": "2026-07-23",
      "campaign_day": 2,
      "topic": "marketing operations",
      "angle": "Automate campaign preparation without automating judgement",
      "headline": "Automate the work around marketing",
      "hook": "Where does marketing operations get stuck?",
      "visual_format": "before-after",
      "keywords": [
        "marketing",
        "operations",
        "workflow",
        "business automation",
        "Sydney business"
      ],
      "source_urls": [],
      "article_slug": "automate-the-work-around-marketing",
      "image_path": "/generated/drafts/2026-07-23/hero.webp",
      "caption_hash": "166b880db5543404b5133a8f5114a83b20056c80d43fc9d424d93441db0a7a55",
      "article_hash": "4c93070e34373dc54a390f4871db555eea144215fed513445881d79dd5cc70a7",
      "status": "generated",
      "website_url": "",
      "instagram_media_id": "",
      "promotion_score": 74,
      "created_at": "2026-07-21T22:03:31.829Z",
      "published_at": "",
      "error": null
    },
    {
      "content_id": "rl-2026-07-24-9a1f7b5584",
      "date": "2026-07-24",
      "campaign_day": 3,
      "topic": "lead qualification",
      "angle": "Collect useful context before a person spends time on the conversation",
      "headline": "Better questions make better calls",
      "hook": "The hidden work around lead qualification",
      "visual_format": "time-returned",
      "keywords": [
        "leads",
        "qualification",
        "sales",
        "business automation",
        "Sydney business"
      ],
      "source_urls": [],
      "article_slug": "better-questions-make-better-calls",
      "image_path": "/generated/drafts/2026-07-24/hero.webp",
      "caption_hash": "25f54f05113ee18f8eeb51d780c2624973e2af6f3bbbc9d715c38e743dbfd515",
      "article_hash": "2399f1e779d0d7a36bd0565cee729886322d9de4079d50f0b8661e1d3f8bd71e",
      "status": "generated",
      "website_url": "",
      "instagram_media_id": "",
      "promotion_score": 78,
      "created_at": "2026-07-21T22:03:32.155Z",
      "published_at": "",
      "error": null
    },
    {
      "content_id": "rl-2026-07-25-9bc939c76c",
      "date": "2026-07-25",
      "campaign_day": 4,
      "topic": "capacity planning",
      "angle": "Use workflow signals to see pressure before it becomes chaos",
      "headline": "See workload before it becomes overload",
      "hook": "See workload before it becomes overload",
      "visual_format": "process-bottleneck",
      "keywords": [
        "capacity",
        "reporting",
        "operations",
        "business automation",
        "Sydney business"
      ],
      "source_urls": [],
      "article_slug": "see-workload-before-it-becomes-overload",
      "image_path": "/generated/drafts/2026-07-25/hero.webp",
      "caption_hash": "199db7a8f34716c53e0b2cb1b24307db22f41186dee2d2dc6cfafc559c1573b5",
      "article_hash": "c9fb5a9560acbdeb00389d19b4455477c35afee686828dcd7e010bd4f0ce030c",
      "status": "generated",
      "website_url": "",
      "instagram_media_id": "",
      "promotion_score": 80,
      "created_at": "2026-07-21T22:03:32.416Z",
      "published_at": "",
      "error": null
    },
    {
      "content_id": "rl-2026-07-26-83d604dcdd",
      "date": "2026-07-26",
      "campaign_day": 5,
      "topic": "software connections",
      "angle": "Use the tools already in place before replacing the stack",
      "headline": "Your software may already be enough",
      "hook": "Where does software connections get stuck?",
      "visual_format": "minimal-data-visual",
      "keywords": [
        "software",
        "integration",
        "cost",
        "business automation",
        "Sydney business"
      ],
      "source_urls": [],
      "article_slug": "your-software-may-already-be-enough",
      "image_path": "/generated/drafts/2026-07-26/hero.webp",
      "caption_hash": "22c9007d87a2379d3a0a559733af68e40dad81a5afcd84835b4083ac1aea505f",
      "article_hash": "8c307c97a585cfe7f0cc908ae5d45e98473162447b4c5296f923114b735958d8",
      "status": "generated",
      "website_url": "",
      "instagram_media_id": "",
      "promotion_score": 80,
      "created_at": "2026-07-21T22:03:32.709Z",
      "published_at": "",
      "error": null
    },
    {
      "content_id": "rl-2026-07-27-a1d0c57cde",
      "date": "2026-07-27",
      "campaign_day": 6,
      "topic": "double handling",
      "angle": "Map the places where the same customer detail is typed twice",
      "headline": "Stop typing the same detail twice",
      "hook": "The hidden work around double handling",
      "visual_format": "before-after",
      "keywords": [
        "data",
        "admin",
        "handover",
        "business automation",
        "Sydney business"
      ],
      "source_urls": [],
      "article_slug": "stop-typing-the-same-detail-twice",
      "image_path": "/generated/drafts/2026-07-27/hero.webp",
      "caption_hash": "f8b9e54d8ebaa0a0130f6cdec845d6b12cec8416134879e472ed19ce0346cb40",
      "article_hash": "1522d073a13ad3c2361d778f0fc77002ae23258e0e10210a8bc7392430996fca",
      "status": "generated",
      "website_url": "",
      "instagram_media_id": "",
      "promotion_score": 72,
      "created_at": "2026-07-21T22:03:32.996Z",
      "published_at": "",
      "error": null
    },
    {
      "content_id": "rl-2026-07-28-9076e735ea",
      "date": "2026-07-28",
      "campaign_day": 7,
      "topic": "owner approvals",
      "angle": "Separate routine rules from decisions that genuinely need the owner",
      "headline": "Not every approval needs the owner",
      "hook": "Not every approval needs the owner",
      "visual_format": "operational-checklist",
      "keywords": [
        "owner",
        "approvals",
        "operations",
        "business automation",
        "Sydney business"
      ],
      "source_urls": [],
      "article_slug": "not-every-approval-needs-the-owner",
      "image_path": "/generated/drafts/2026-07-28/hero.webp",
      "caption_hash": "67cb7121b89eb37c5960f5cc9ab83a82d0a2454d18c64c49fd295e78e55cc712",
      "article_hash": "aaf313224c887b2eef7cd34607a087c741f3bd34b6b1f07fccc1732763210987",
      "status": "generated",
      "website_url": "",
      "instagram_media_id": "",
      "promotion_score": 79,
      "created_at": "2026-07-21T22:03:33.288Z",
      "published_at": "",
      "error": null
    },
    {
      "content_id": "rl-2026-07-29-23d3da1970",
      "date": "2026-07-29",
      "campaign_day": 8,
      "topic": "weekly reporting",
      "angle": "Build the report once, then make the source systems feed it",
      "headline": "Stop rebuilding Friday’s report",
      "hook": "Where does weekly reporting get stuck?",
      "visual_format": "decision-tree",
      "keywords": [
        "reporting",
        "visibility",
        "data",
        "business automation",
        "Sydney business"
      ],
      "source_urls": [],
      "article_slug": "stop-rebuilding-fridays-report",
      "image_path": "/generated/drafts/2026-07-29/hero.webp",
      "caption_hash": "763451bccbf30bf86be49fcb689df35da57576c593d9f055bbeddd9e6ea46979",
      "article_hash": "7e8a624685ac20fefdf1428acc950e22bb05cf69f06720efce51263747bfb2df",
      "status": "generated",
      "website_url": "",
      "instagram_media_id": "",
      "promotion_score": 78,
      "created_at": "2026-07-21T22:03:33.555Z",
      "published_at": "",
      "error": null
    },
    {
      "content_id": "rl-2026-07-30-a0519a09dc",
      "date": "2026-07-30",
      "campaign_day": 9,
      "topic": "customer updates",
      "angle": "Send predictable progress updates without losing the personal relationship",
      "headline": "Silence creates avoidable follow-up",
      "hook": "The hidden work around customer updates",
      "visual_format": "before-after",
      "keywords": [
        "customers",
        "communication",
        "workflow",
        "business automation",
        "Sydney business"
      ],
      "source_urls": [],
      "article_slug": "silence-creates-avoidable-follow-up",
      "image_path": "/generated/drafts/2026-07-30/hero.webp",
      "caption_hash": "804f385876e266c46df2fbd90c5405a3a92b4f894885957c58f4c9b42e9495e2",
      "article_hash": "37dcf6b4a61ea94a38a28f1fb713ed86d806e5d32828347a56c4fb90d0462613",
      "status": "generated",
      "website_url": "",
      "instagram_media_id": "",
      "promotion_score": 75,
      "created_at": "2026-07-21T22:03:33.850Z",
      "published_at": "",
      "error": null
    },
    {
      "content_id": "rl-2026-07-31-3e2c09e2a2",
      "date": "2026-07-31",
      "campaign_day": 10,
      "topic": "enquiry follow-up",
      "angle": "Why fast acknowledgement and human follow-up should be separate steps",
      "headline": "A good lead should never wait for an acknowledgement",
      "hook": "A good lead should never wait for an acknowledgement",
      "visual_format": "workflow-diagram",
      "keywords": [
        "leads",
        "follow-up",
        "crm",
        "business automation",
        "Sydney business"
      ],
      "source_urls": [],
      "article_slug": "a-good-lead-should-never-wait-for-an-acknowledgement",
      "image_path": "/generated/drafts/2026-07-31/hero.webp",
      "caption_hash": "a6e467777a594696e95d3e901a4373972765c7d06eede12aaf820777bb8b5a8d",
      "article_hash": "bd2290b7e91df95e75ffd6e0a38dd02de89c90f63fab6f070e61fac3326d9ab9",
      "status": "generated",
      "website_url": "",
      "instagram_media_id": "",
      "promotion_score": 72,
      "created_at": "2026-07-21T22:03:34.114Z",
      "published_at": "",
      "error": null
    },
    {
      "content_id": "rl-2026-08-01-3add45e01a",
      "date": "2026-08-01",
      "campaign_day": 11,
      "topic": "job handover",
      "angle": "Make ownership and the next action visible at every handover",
      "headline": "Handover gaps create hidden work",
      "hook": "Where does job handover get stuck?",
      "visual_format": "practical-principle",
      "keywords": [
        "handover",
        "operations",
        "accountability",
        "business automation",
        "Sydney business"
      ],
      "source_urls": [],
      "article_slug": "handover-gaps-create-hidden-work",
      "image_path": "/generated/drafts/2026-08-01/hero.webp",
      "caption_hash": "07d2c593e8aa7fd79b9caa80e789265c70fb0edf5e89150b904da2728694b5d0",
      "article_hash": "3d803a9166e01d056e409ed6614cb622892f484a854f0ebb61a802b8cf3233f8",
      "status": "generated",
      "website_url": "",
      "instagram_media_id": "",
      "promotion_score": 79,
      "created_at": "2026-07-21T22:03:34.415Z",
      "published_at": "",
      "error": null
    },
    {
      "content_id": "rl-2026-08-02-88c9552625",
      "date": "2026-08-02",
      "campaign_day": 12,
      "topic": "inbox triage",
      "angle": "Route routine messages before they become an owner bottleneck",
      "headline": "Your inbox is not a workflow",
      "hook": "The hidden work around inbox triage",
      "visual_format": "process-bottleneck",
      "keywords": [
        "email",
        "triage",
        "operations",
        "business automation",
        "Sydney business"
      ],
      "source_urls": [],
      "article_slug": "your-inbox-is-not-a-workflow",
      "image_path": "/generated/drafts/2026-08-02/hero.webp",
      "caption_hash": "6f43319550751fd7605990c112359cfaba93ca91d2205747cee6e37befc4f884",
      "article_hash": "90bd40f8466ab98dd1b982fb8f041e6aff369072d24dff5264fbae2cc470c7e5",
      "status": "generated",
      "website_url": "",
      "instagram_media_id": "",
      "promotion_score": 74,
      "created_at": "2026-07-21T22:03:34.712Z",
      "published_at": "",
      "error": null
    },
    {
      "content_id": "rl-2026-08-03-9b686ab4d5",
      "date": "2026-08-03",
      "campaign_day": 13,
      "topic": "invoice preparation",
      "angle": "Move approved job information into invoicing without retyping",
      "headline": "Finished work should flow to invoicing",
      "hook": "Finished work should flow to invoicing",
      "visual_format": "operational-checklist",
      "keywords": [
        "invoicing",
        "finance",
        "handover",
        "business automation",
        "Sydney business"
      ],
      "source_urls": [],
      "article_slug": "finished-work-should-flow-to-invoicing",
      "image_path": "/generated/drafts/2026-08-03/hero.webp",
      "caption_hash": "f3e11d864ff3f62993f71fa7be5ff7f3fd1963b8044313a6a242add754cd585a",
      "article_hash": "33f4ee215b647fee210d3f3961ddbeee3710b96cff4ba6f9de2227efd23eca3d",
      "status": "generated",
      "website_url": "",
      "instagram_media_id": "",
      "promotion_score": 74,
      "created_at": "2026-07-21T22:03:35.014Z",
      "published_at": "",
      "error": null
    },
    {
      "content_id": "rl-2026-08-04-e564a4a4e8",
      "date": "2026-08-04",
      "campaign_day": 14,
      "topic": "task creation",
      "angle": "Create the next task from the event that actually triggers it",
      "headline": "The next task should create itself",
      "hook": "Where does task creation get stuck?",
      "visual_format": "process-bottleneck",
      "keywords": [
        "tasks",
        "workflow",
        "handover",
        "business automation",
        "Sydney business"
      ],
      "source_urls": [],
      "article_slug": "the-next-task-should-create-itself",
      "image_path": "/generated/drafts/2026-08-04/hero.webp",
      "caption_hash": "3441ad0e4260a306b0ef590ffe47d0d6a9bb41b6178e29b22c10517e23ea6ed7",
      "article_hash": "7bc3ecc9110c4137dae0ffbe8d650cdfb9de00609b7bc03b217350f0b745832a",
      "status": "generated",
      "website_url": "",
      "instagram_media_id": "",
      "promotion_score": 75,
      "created_at": "2026-07-21T22:03:35.252Z",
      "published_at": "",
      "error": null
    }
  ]
}
